setup.py
myAnimals/Birds.py
myAnimals/Mammals.py
myAnimals/__init__.py
myAnimals.egg-info/PKG-INFO
myAnimals.egg-info/SOURCES.txt
myAnimals.egg-info/dependency_links.txt
myAnimals.egg-info/top_level.txt
myAnimals.egg-info/Animals/Birds.py
myAnimals.egg-info/Animals/Mammals.py
myAnimals.egg-info/Animals/__init__.py
myAnimals.egg-info/Animals/__pycache__/__init__.cpython-36.pyc