Metadata-Version: 1.0
Name: myAnimals
Version: 0.0.0
Summary: Distinguish mammals and birds
Home-page: UNKNOWN
Author: Saeed Mirshekari
Author-email: saeed.mirshekari@gmail.com
License: MIT
Platform: UNKNOWN
